{
    "codeLens.enable": true,
    "solargraph.useBundler": false,
    "solargraph.formatting": true,
    "solargraph.diagnostics": true,
    "diagnostic.checkCurrentLine": true,
    "sourcekit.commandPath": "/usr/bin/sourcekit-lsp",
    "sourcekit.filetypes": ["swift"],
    "python.formatting.blackPath": "/usr/local/bin/black",
    "python.pythonPath": "/Users/marcelo.aguiar/.pyenv/shims/python3",
    "python.analysis.autoSearchPaths": true,
    "python.analysis.useLibraryCodeForTypes": true,
    "python.linting.enabled": true,
    "python.linting.pylintEnabled": true,
    "python.formatting.provider": "black",
    "python.formatting.blackPath": "/opt/homebrew/bin/black",
    "python.analysis.diagnosticMode": "workspace",
    "python.analysis.typeCheckingMode": "basic"
}
